mpijobs.py
version.py
mpijobs-0.2.2.dist-info/DESCRIPTION.rst
mpijobs-0.2.2.dist-info/WHEEL
mpijobs-0.2.2.dist-info/top_level.txt
mpijobs-0.2.2.dist-info/metadata.json
mpijobs-0.2.2.dist-info/RECORD
mpijobs-0.2.2.dist-info/METADATA
