Metadata-Version: 2.0
Name: mpijobs
Version: 0.2.2
Summary: Run many jobs using MPI processes through a master/slave approach
Home-page: https://github.com/ziotom78/mpijobs
Author: Maurizio Tomasi
Author-email: ziotom78@gmail.com
License: MIT
Keywords: mpi master/slave
Platform: UNKNOWN
Classifier: Programming Language :: Python
Classifier: Programming Language :: Python :: 3 :: Only
Classifier: Development Status :: 3 - Alpha
Classifier: Intended Audience :: Science/Research
Classifier: License :: OSI Approved :: MIT License
Classifier: Operating System :: OS Independent
Classifier: Topic :: Software Development
Classifier: Topic :: System :: Distributed Computing
Requires-Dist: mpi4py
